spiffyline/__init__.py
spiffyline/logger/__init__.py
spiffyline/theme/__init__.py
spiffyline/theme/exceptions.py
spiffyline-1.0.dist-info/LICENSE
spiffyline-1.0.dist-info/METADATA
spiffyline-1.0.dist-info/WHEEL
spiffyline-1.0.dist-info/top_level.txt
spiffyline-1.0.dist-info/RECORD
