Metadata-Version: 2.1
Name: spiffyline
Version: 1.0
Summary: Spiff up your CLI with color, formatting, and utilities
Home-page: https://github.com/snakeyworm/spiffyline
Author: Caleb Loera
License: UNKNOWN
Platform: UNKNOWN
Classifier: Programming Language :: Python :: 3
Classifier: License :: OSI Approved :: MIT License
Classifier: Operating System :: OS Independent
Classifier: Environment :: Console
Requires-Python: >=3.6
